PythonDoc2734/README.md
PythonDoc2734/__init__.py
PythonDoc2734/__main__.py
PythonDoc2734/file.epub
PythonDoc2734/index.html
PythonDoc2734/css/__init__.py
PythonDoc2734/css/annotations.css
PythonDoc2734/css/main.css
PythonDoc2734/css/normalize.css
PythonDoc2734/css/popup.css
PythonDoc2734/font/__init__.py
PythonDoc2734/font/fontello.eot
PythonDoc2734/font/fontello.svg
PythonDoc2734/font/fontello.ttf
PythonDoc2734/font/fontello.woff
PythonDoc2734/img/__init__.py
PythonDoc2734/img/annotator-glyph-sprite.png
PythonDoc2734/img/annotator-icon-sprite.png
PythonDoc2734/img/apple-touch-icon.png
PythonDoc2734/img/cancelfullscreen.png
PythonDoc2734/img/close.png
PythonDoc2734/img/fullscreen.png
PythonDoc2734/img/loader.gif
PythonDoc2734/img/menu-icon.png
PythonDoc2734/img/save.png
PythonDoc2734/img/saved.png
PythonDoc2734/img/settings-s.png
PythonDoc2734/img/settings.png
PythonDoc2734/img/star.png
PythonDoc2734/js/__init__.py
PythonDoc2734/js/epub.js
PythonDoc2734/js/epub.min.js
PythonDoc2734/js/epub.min.map
PythonDoc2734/js/hooks.min.js
PythonDoc2734/js/hooks.min.map
PythonDoc2734/js/reader.js
PythonDoc2734/js/reader.js.map
PythonDoc2734/js/reader.min.js
PythonDoc2734/js/reader.min.map
PythonDoc2734/js/hooks/__init__.py
PythonDoc2734/js/hooks/extensions/__init__.py
PythonDoc2734/js/hooks/extensions/highlight.js
PythonDoc2734/js/libs/__init__.py
PythonDoc2734/js/libs/jquery.min.js
PythonDoc2734/js/libs/localforage.min.js
PythonDoc2734/js/libs/screenfull.js
PythonDoc2734/js/libs/screenfull.min.js
PythonDoc2734/js/libs/zip.min.js
PythonDoc2734/js/plugins/__init__.py
PythonDoc2734/js/plugins/hypothesis.js
PythonDoc2734/js/plugins/search.js
python_doc_27_34-2024.3.2.0.dist-info/METADATA
python_doc_27_34-2024.3.2.0.dist-info/WHEEL
python_doc_27_34-2024.3.2.0.dist-info/entry_points.txt
python_doc_27_34-2024.3.2.0.dist-info/top_level.txt
python_doc_27_34-2024.3.2.0.dist-info/RECORD
